VASA/BasePlot.py
VASA/__init__.py
VASA/reduce_vasa_df.py
VASA/scatter.py
VASA/stripplot.py
VASA/stripplot_ol.py
VASA/summaryplot.py
VASA/vasa.py
VASA-0.0.1.dist-info/LICENSE
VASA-0.0.1.dist-info/METADATA
VASA-0.0.1.dist-info/WHEEL
VASA-0.0.1.dist-info/top_level.txt
VASA-0.0.1.dist-info/RECORD
